ccpr/__init__.py
ccpr-1.0.2.dist-info/LICENSE
ccpr-1.0.2.dist-info/METADATA
ccpr-1.0.2.dist-info/WHEEL
ccpr-1.0.2.dist-info/entry_points.txt
ccpr-1.0.2.dist-info/top_level.txt
ccpr-1.0.2.dist-info/RECORD
