Metadata-Version: 2.1
Name: ccpr
Version: 1.0.2
Summary: AWS CodeCommit PR CLI
Home-page: https://github.com/rog555/ccpr
Author: Roger Foskett
Author-email: r_foskett@hotmail.com
License: Apache License 2.0
Platform: UNKNOWN
Classifier: Programming Language :: Python :: 3
Classifier: License :: OSI Approved :: Apache Software License
Classifier: Operating System :: OS Independent
Requires-Dist: argcomplete (==1.12.3)
Requires-Dist: argh (==0.26.2)
Requires-Dist: boto3 (==1.21.31)
Requires-Dist: jmespath (==0.10.0)
Requires-Dist: rich (==12.0.1)
Requires-Dist: timeago (==1.0.15)
